{
    "Delivery service": "Delivery service",
    "About us": "About us",
    "Contacts": "Contacts",
    "en": "en",
    "ua": "ua",
    "Logistics made easy": "Logistics made easy",
    "through digital solutions": "through digital solutions",
    "description": "We make it easy to manage your shipments and logistics online. From finding a price and making bookings to submitting documents and tracking cargo.",
    "Login": "Login",
    "email": "email",
    "password": "password",
    "Forget Password?": "Forget Password?",
    "Dont't have an account?": "Dont't have an account?",
    "Sign up": "Sign up",
    "Logout": "Logout",
    "Language": "Language",
    "English": "EN",
    "Ukrainian": "UA",
    "textForgotPassword": "Please fill in your email below and we will send you an email with instructions on how to reset your password.",
    "Forgot password": "Forgot password",
    "Registration": "Registration",
    "Submit": "Submit",
    "Cancel": "Cancel",
    "Forgot Password?": "Forgot Password?",
    "Name": "Name",
    "Email": "Email",
    "Password": "Password",
    "Rules": "Rules",
    "Email should be required": "Email should be required",
    "Invalid email": "Invalid email",
    "UserName should be required": "UserName should be required",
    "Length must be at least 3 characters": "Length must be at least 3 characters",
    "Password should be required": "Password should be required",
    "Length must be at least 6 characters": "Length must be at least 6 characters",
    "Role": "Role",
    "Role should be required": "Role should be required",
    "Enter your registered email":"Enter your registered email",
    "Password change instructions have been sent to your email": "Password change instructions have been sent to your email",
    "Go to Login page": "Go to Login page",
    "Enter new password": "Enter new password",
    "Password changed successfully": "Password changed successfully",
    "Back to home page": "Back to home page",
    "You don't have any active loads yet.": "You don't have any active loads yet.",
    "Profile": "Profile",
    "Edit personal data": "Edit personal data",
    "Change password": "Change password",
    "Delete profile": "Delete profile",
    "Username": "Username",
    "Save": "Save",
    "Upload a photo": "Upload a photo",
    "Delete photo": "Delete photo",
    "Enter an old password": "Enter an old password",
    "Enter a new password": "Enter a new password",
    "Confirm the password": "Confirm the password",
    "Passwords must match": "Passwords must match",
    "Are you sure you want to delete the profile?": "Are you sure you want to delete the profile?",
    "No": "No",
    "Yes": "Yes",
    "Add truck": "Add truck",
    "Add load": "Add load",
    "Type of truck": "Type of truck",
    "Status": "Status",
    "Assigned to": "Assigned to",
    "Created date": "Created date",
    "Load name": "Load name",
    "Pickup address": "Pickup address",
    "Delivery address": "Delivery address",
    "Update": "Update",
    "Delete": "Delete",
    "Details": "Details",
    "Assign the truck": "Assign the truck",
    "Enter type...": "Enter type...",
    "Type": "Type",
    "Type should be required": "Type should be required",
    "Invalid type": "Invalid type",
    "Available truck types: sprinter, small stright, large stright": "Available truck types: sprinter, small stright, large stright",
    "Add changes": "Add changes",
    "Created by/User Id": "Created by/User Id",
    "Filter by name...": "Filter by name...",
    "Truck search": "Truck search",
    "Create load": "Create load",
    "Update load": "Update load",
    "Enter name...": "Enter name...",
    "Payload": " Payload",
    "Name should be required": "Name should be required",
    "Length must be at least 4 characters": "Length must be at least 4 characters",
    "Name should be a string": "Name should be a string",
    "Enter payload...": "Enter payload...",
    "Payload should be required": "Payload should be required",
    "Payload should be a number": "Payload should be a number",
    "Payload should be no higher than 4000": "Payload should be no higher than 4000",
    "Enter pickup address...": "Enter pickup address...",
    "Pickup address should be required": "Pickup address should be required",
    "Length must be at least 15 characters": "Length must be at least 15 characters",
    "Pickup address should be a string": "Pickup address should be a string",
    "Addresses must not match": "Addresses must not match",
    "Enter delivery address...": "Enter delivery address...",
    "Delivery address should be required": "Delivery address should be required",
    "Delivery address should be a string": "Delivery address should be a string",
    "Enter dimensions:": "Enter dimensions:",
    "Enter width...": "Enter width...",
    "Width": "Width",
    "Width should be required": "Width should be required",
    "Width should be a number": "Width should be a number",
    "Width should be no higher than 700": "Width should be no higher than 700",
    "Enter length...": "Enter length...",
    "Length": "Length",
    "Length should be required": "Length should be required",
    "Length should be a number": "Length should be a number",
    "Length should be no higher than 350": "Length should be no higher than 350",
    "Enter height...": "Enter height...",
    "Height": "Height",
    "Height should be required": "Height should be required",
    "Height should be a number": "Height should be a number",
    "Height should be no higher than 200": "Height should be no higher than 200",
    "Change to next state": "Change to next state",
    "Pick up load": "Pick up load",
    "State": "State",
    "Dimensions": "Dimensions",
    "Truck info": "Truck info",
    "Truck ID": "Truck ID",
    "Load ID": "Load ID",
    "You haven't created any": "You haven't created any",
    "yet": "yet",
    "loads": "loads",
    "trucks": "trucks",
    "Active Loads": "Active Loads",
    "Archive Loads": "Archive Loads",
    "type Asc": "type Asc",
    "Without sort": "Without sort"  
}